asn1tools/__init__.py
asn1tools/__main__.py
asn1tools/compat.py
asn1tools/compiler.py
asn1tools/errors.py
asn1tools/parser.py
asn1tools/version.py
asn1tools/codecs/__init__.py
asn1tools/codecs/ber.py
asn1tools/codecs/compiler.py
asn1tools/codecs/constraints_checker.py
asn1tools/codecs/der.py
asn1tools/codecs/gser.py
asn1tools/codecs/jer.py
asn1tools/codecs/oer.py
asn1tools/codecs/per.py
asn1tools/codecs/permitted_alphabet.py
asn1tools/codecs/type_checker.py
asn1tools/codecs/uper.py
asn1tools/codecs/xer.py
asn1tools/source/__init__.py
asn1tools/source/c/__init__.py
asn1tools/source/c/oer.py
asn1tools/source/c/uper.py
asn1tools/source/c/utils.py
asn1tools/source/rust/__init__.py
asn1tools/source/rust/uper.py
asn1tools/source/rust/utils.py
asn1tools-0.152.0.dist-info/LICENSE
asn1tools-0.152.0.dist-info/METADATA
asn1tools-0.152.0.dist-info/WHEEL
asn1tools-0.152.0.dist-info/entry_points.txt
asn1tools-0.152.0.dist-info/top_level.txt
asn1tools-0.152.0.dist-info/RECORD
