Metadata-Version: 2.1
Name: asn1tools
Version: 0.152.0
Summary: ASN.1 parsing, encoding and decoding.
Home-page: https://github.com/eerimoq/asn1tools
Author: Erik Moqvist
Author-email: erik.moqvist@gmail.com
License: MIT
Keywords: ASN.1,asn1
Platform: UNKNOWN
Classifier: License :: OSI Approved :: MIT License
Classifier: Programming Language :: Python :: 2
Classifier: Programming Language :: Python :: 3
Requires-Dist: bitstruct
Requires-Dist: diskcache
Requires-Dist: prompt-toolkit
Requires-Dist: pyparsing (>=2.2.0)
